jsonapi_orm/__init__.py
jsonapi_orm/jsonapi_orm.py
jsonapi_orm-0.1.8.dist-info/DESCRIPTION.rst
jsonapi_orm-0.1.8.dist-info/LICENSE.txt
jsonapi_orm-0.1.8.dist-info/METADATA
jsonapi_orm-0.1.8.dist-info/RECORD
jsonapi_orm-0.1.8.dist-info/WHEEL
jsonapi_orm-0.1.8.dist-info/metadata.json
jsonapi_orm-0.1.8.dist-info/top_level.txt
