Metadata-Version: 2.0
Name: jsonapi-orm
Version: 0.1.8
Summary: Quick and dirty ORM that maps JSON:API responses to object attributes.
Home-page: https://github.com/mislavcimpersak/jsonapi-orm
Author: Mislav Cimperšak
Author-email: mislav.cimpersak@gmail.com
License: BSD license
Keywords: jsonapi-orm
Platform: UNKNOWN
Classifier: Development Status :: 2 - Pre-Alpha
Classifier: Intended Audience :: Developers
Classifier: License :: OSI Approved :: BSD License
Classifier: Natural Language :: English
Classifier: Programming Language :: Python :: 3
Classifier: Programming Language :: Python :: 3.5
Classifier: Programming Language :: Python :: 3.6
Requires-Dist: munch
